[
    {
        "text": "#short #watchlist for #trading on #nyse #nasdaq between $150 and $200: $AMT $AVB $AYI $ENPH",
        "author": "Simon's Trade",
        "author_verified": true,
        "date": "2023-06-22T20:29:43.000Z",
        "link": "https://twitter.com/simonstradeinc/status/1671978795987771419",
        "author_profile_pic": "",
        "image": ""
    },
    {
        "text": "Multifam #REIT balance sheets are very low leverage across the board $CPT $EQR $AVB $ESS $UDR. Nice opp here IMO as new const likely to be pretty low given rates/const costs/bank turmoil. While lots of supply coming in sunbelt in 23-24, s/b very low in 25-26. W/ dev expertise",
        "author": "Private Eye Capital",
        "author_verified": true,
        "date": "2023-06-23T23:06:07.000Z",
        "link": "https://twitter.com/PrivateEyeCap/status/1672380543055585281",
        "author_profile_pic": "",
        "image": ""
    },
    {
        "text": "$AVB  new alert at http://timent.html?user=usequities\u2026 #stocks #daytrading #NYSE #NASDAQ #market 390",
        "author": "Media Sentiment\u00ae",
        "author_verified": true,
        "date": "2023-06-23T14:55:12.000Z",
        "link": "https://twitter.com/mediasentiment/status/1672256999151525889",
        "author_profile_pic": "",
        "image": ""
    },
    {
        "text": "and a strong B/S, $MAA $CPT $AVB can develop for delivery into what should be a very strong market. Also well positioned to pick up new assets in lease up on the cheap as merchant builders may have to puke assets over the next 12-18 mos",
        "author": "Private Eye Capital",
        "author_verified": true,
        "date": "2023-06-23T23:07:41.000Z",
        "link": "https://twitter.com/PrivateEyeCap/status/1672380939551506432",
        "author_profile_pic": "",
        "image": ""
    },
    {
        "text": "20 DMA Support today: $REG $MFV $JCPB $EMLP $LMNR $DOGZ $IGRO $GMFI $ACHR $BHV $AVB $GEF.B $GECC $NHS $MASI $TPYP $BFST $TRV $FHN $RNXT ...",
        "author": "SwingTradeBot",
        "author_verified": true,
        "date": "2023-06-22T16:25:23.000Z",
        "link": "https://twitter.com/SwingTradeBot/status/1671917306811670528",
        "author_profile_pic": "",
        "image": ""
    },
    {
        "text": "Nice print for $AVB Size: 104870 Price: 186.02 Amount: $19,507,917.40 Time: 1830\nSee more: https://\nJoin https:// to get REAL TIME prints.\nRunners : https://\nLosers : https://\nGappers : https://",
        "author": "TradeWithAlerts",
        "author_verified": true,
        "date": "2023-06-26T22:30:01.000Z",
        "link": "https://twitter.com/TradeWithAlerts/status/1673458621135618048",
        "author_profile_pic": "",
        "image": ""
    },
    {
        "text": "Nice print for $AVB Size: 101343 Price: 184.99 Amount: $18,747,441.57 Time: 1900\nSee more: https://\nJoin https:// to get REAL TIME prints.\nRunners : https://\nLosers : https://\nGappers : https://",
        "author": "TradeWithAlerts",
        "author_verified": true,
        "date": "2023-06-22T23:00:03.000Z",
        "link": "https://twitter.com/TradeWithAlerts/status/1672016630417702914",
        "author_profile_pic": "",
        "image": ""
    }
]