[
    {
        "text": "Top #moneyflow for whole #market today\n$HYDW $AMD $NTRS $IWM $SPTS $IBDO $BAC $SPTI $MSFT $MTUM ...",
        "author": "TickWatcher",
        "author_verified": true,
        "date": "2023-06-22T20:05:01.000Z",
        "link": "https://twitter.com/MITickWatcher/status/1671972581266853888",
        "author_profile_pic": "",
        "image": ""
    },
    {
        "text": "#short #watchlist for #trading on #nyse #nasdaq between $70 and $80: $APO $LBRDK $NTRS $VOYA",
        "author": "Simon's Trade",
        "author_verified": true,
        "date": "2023-06-22T20:28:06.000Z",
        "link": "https://twitter.com/simonstradeinc/status/1671978387387064340",
        "author_profile_pic": "",
        "image": ""
    },
    {
        "text": "Unusual volume stocks today:\n$NTRS $FDS $CCI $TRU $SRPT $ERIE $DRI $SEDG $BBDO $DEO",
        "author": "Betty Thompson",
        "author_verified": true,
        "date": "2023-06-22T21:46:25.000Z",
        "link": "https://twitter.com/BettytThompson/status/1671998100326477828",
        "author_profile_pic": "",
        "image": ""
    },
    {
        "text": "DOWNSIDE MOMO: $NTRS Northern Trust Corporation  promo: LUV15  http://",
        "author": "Trade Alerts, Trade Ideas and Crypto ",
        "author_verified": true,
        "date": "2023-06-22T19:08:09.000Z",
        "link": "https://twitter.com/AlertTrade/status/1671958269005549568",
        "author_profile_pic": "",
        "image": ""
    },
    {
        "text": "Nice print for $NTRS Size: 235481 Price: 72.95 Amount: $17,178,338.95 Time: 1600\nSee more: https://\nJoin https:// to get REAL TIME prints.\nRunners : https://\nLosers : https://\nGappers : https://",
        "author": "TradeWithAlerts",
        "author_verified": true,
        "date": "2023-06-21T20:00:00.000Z",
        "link": "https://twitter.com/TradeWithAlerts/status/1671608930605178880",
        "author_profile_pic": "",
        "image": ""
    },
    {
        "text": "Nice print for $NTRS Size: 114770 Price: 71.75 Amount: $8,234,747.50 Time: 1600\nSee more: https://\nJoin https:// to get REAL TIME prints.\nRunners : https://\nLosers : https://\nGappers : https://",
        "author": "TradeWithAlerts",
        "author_verified": true,
        "date": "2023-06-22T20:00:00.000Z",
        "link": "https://twitter.com/TradeWithAlerts/status/1671971318336479232",
        "author_profile_pic": "",
        "image": ""
    }
]